<intent-filter>
  <action android:name="android.intent.action.VIEW" />
  <category android:name="android.intent.category.DEFAULT" />
  <data android:mimeType="text/csv" />
  <data android:scheme="file" />
  <data android:host="*" />
  <data android:port="*" />
  <data android:pathPattern=".*..*..*..*..*.csv" />
  <data android:pathPattern=".*..*..*..*.csv" />
  <data android:pathPattern=".*..*..*.csv" />
  <data android:pathPattern=".*..*.csv" />
  <data android:pathPattern=".*.csv" />
</intent-filter>
